test
vincrosscheck
