Metadata-Version: 1.0
Name: vincrosscheck-api-python-client
Version: 1.0.6
Summary: VXC Services API
Home-page: UNKNOWN
Author: UNKNOWN
Author-email: UNKNOWN
License: UNKNOWN
Keywords: Swagger,VXC Services API
Platform: UNKNOWN
